{
  "active": false,
  "connections": {},
  "createdAt": "2024-12-20T16:06:13.825Z",
  "id": "urGp9NdypVxjI7Qv",
  "meta": null,
  "name": "Post Gumroad offer codes from SM",
  "nodes": [
    {
      "parameters": {
        "url": "https://api.gumroad.com/v2/products/A-m3CDDC5dlrSdKZp0RFhA==/offer_codes",
        "sendBody": true,
        "contentType": "form-urlencoded",
        "bodyParameters": {
          "parameters": [
            {
              "name": "access_token",
              "value": "tJqRgo85uqkjM8UU95H2XmfWvLH5H2_yKG5bL2AVHPw"
            }
          ]
        },
        "options": {}
      },
      "id": "46338bd5-dd89-4eef-938e-6f40b857032e",
      "name": "list offer codes",
      "type": "n8n-nodes-base.httpRequest",
      "typeVersion": 4.2,
      "position": [
        -360,
        200
      ]
    }
  ],
  "pinData": null,
  "settings": {
    "executionOrder": "v1"
  },
  "staticData": null,
  "tags": [],
  "triggerCount": 0,
  "updatedAt": "2024-12-20T16:06:13.825Z",
  "versionId": "05f32c16-a47b-408b-a629-59b791a1a470"
}